multivis/Edge.py
multivis/Network.py
multivis/__init__.py
multivis/__version__.py
multivis/clustermap.py
multivis/edgeBundle.py
multivis/forceNetwork.py
multivis/pca.py
multivis/pcaLoadings.py
multivis/pcoa.py
multivis/plotFeatures.py
multivis/plotNetwork.py
multivis/polarDendrogram.py
multivis/springNetwork.py
multivis/utils/__init__.py
multivis/utils/cluster.py
multivis/utils/corrAnalysis.py
multivis/utils/groups2blocks.py
multivis/utils/imputeData.py
multivis/utils/loadData.py
multivis/utils/mergeBlocks.py
multivis/utils/range_scale.py
multivis/utils/scaleData.py
multivis/utils/scaler.py
multivis/utils/statistics.py
multivis/utils/transform.py
multivis-0.5.12.dist-info/LICENSE.txt
multivis-0.5.12.dist-info/METADATA
multivis-0.5.12.dist-info/WHEEL
multivis-0.5.12.dist-info/top_level.txt
multivis-0.5.12.dist-info/RECORD
