Metadata-Version: 2.1
Name: multivis
Version: 0.5.12
Summary: MultiVis is a data visualisation package that produces both static and interactive visualisations targeted towards the Omics community.
Home-page: https://github.com/brettChapman/multivis
Author: Brett Chapman
Author-email: brett.chapman@murdoch.edu.au, brett.chapman78@gmail.com
License: MIT License
Requires-Python: ==3.11.4
License-File: LICENSE.txt
Requires-Dist: numpy ==1.25.2
Requires-Dist: openpyxl ==3.1.2
Requires-Dist: pandas ==2.1.0
Requires-Dist: matplotlib ==3.8.0
Requires-Dist: seaborn ==0.12.2
Requires-Dist: networkx ==3.1.0
Requires-Dist: statsmodels ==0.14.0
Requires-Dist: scikits-bootstrap ==1.1.0
Requires-Dist: scipy ==1.11.2
Requires-Dist: scikit-learn ==1.3.1
Requires-Dist: tqdm ==4.66.1
Requires-Dist: xlrd ==2.0.1
